fb_vmware/__init__.py
fb_vmware/about.py
fb_vmware/base.py
fb_vmware/cluster.py
fb_vmware/connect.py
fb_vmware/controller.py
fb_vmware/datastore.py
fb_vmware/dc.py
fb_vmware/disk.py
fb_vmware/ds_cluster.py
fb_vmware/dvs.py
fb_vmware/errors.py
fb_vmware/ether.py
fb_vmware/host.py
fb_vmware/host_port_group.py
fb_vmware/iface.py
fb_vmware/local_version.py
fb_vmware/network.py
fb_vmware/obj.py
fb_vmware/typed_dict.py
fb_vmware/vm.py
fb_vmware/xlate.py
fb_vmware/app/__init__.py
fb_vmware/app/get_host_list.py
fb_vmware/app/get_network_list.py
fb_vmware/app/get_storage_cluster_list.py
fb_vmware/app/get_vm_info.py
fb_vmware/app/get_vm_list.py
fb_vmware/config/__init__.py
fb_vmware-1.5.3.data/data/share/locale/de_DE/LC_MESSAGES/fb_vmware.mo
fb_vmware-1.5.3.data/data/share/locale/en_US/LC_MESSAGES/fb_vmware.mo
fb_vmware-1.5.3.data/scripts/get-vsphere-host-list
fb_vmware-1.5.3.data/scripts/get-vsphere-network-list
fb_vmware-1.5.3.data/scripts/get-vsphere-storage-cluster-list
fb_vmware-1.5.3.data/scripts/get-vsphere-vm-info
fb_vmware-1.5.3.data/scripts/get-vsphere-vm-list
fb_vmware-1.5.3.dist-info/licenses/LICENSE
fb_vmware-1.5.3.dist-info/METADATA
fb_vmware-1.5.3.dist-info/WHEEL
fb_vmware-1.5.3.dist-info/top_level.txt
fb_vmware-1.5.3.dist-info/RECORD
