Metadata-Version: 2.4
Name: fb_vmware
Version: 1.5.3
Summary: A wrapper module around the pyvmomi module to simplify work and handling.
Home-page: https://github.com/fbrehm/fb-vmware
Author: Frank Brehm
Author-email: frank@brehm-online.com
License: LGPL3+
Platform: posix
Classifier: Development Status :: 4 - Beta
Classifier: Environment :: Console
Classifier: Intended Audience :: Developers
Classifier: License :: OSI Approved :: GNU Lesser General Public License v3 or later (LGPLv3+)
Classifier: Natural Language :: English
Classifier: Operating System :: POSIX
Classifier: Programming Language :: Python :: 3.6
Classifier: Programming Language :: Python :: 3.7
Classifier: Programming Language :: Python :: 3.8
Classifier: Programming Language :: Python :: 3.9
Classifier: Programming Language :: Python :: 3.10
Classifier: Programming Language :: Python :: 3.11
Classifier: Programming Language :: Python :: 3.12
Classifier: Topic :: Software Development :: Libraries :: Python Modules
Requires: fb_tools
Requires: argparse
Requires: six
Requires: pyvmomi
Requires: fb_logging
Requires: packaging
Requires: requests
Requires: pytz
Requires: setuptools
Requires: wheel
Requires: Babel
Requires: PyYAML
Requires: toml
Provides: fb_vmware
License-File: LICENSE
Requires-Dist: fb_logging
Requires-Dist: fb_tools
Requires-Dist: pytz
Requires-Dist: requests
Requires-Dist: Babel
Requires-Dist: pyvmomi
Dynamic: description
Dynamic: license-file
Dynamic: provides
Dynamic: requires
